pyportal/__init__.py
pyportal/api.py
pyportal/constants.py
pyportal/endpoints.py
pyportal/errors.py
pyportal/iterators.py
nhm_pyportal-0.1.dist-info/METADATA
nhm_pyportal-0.1.dist-info/WHEEL
nhm_pyportal-0.1.dist-info/entry_points.txt
nhm_pyportal-0.1.dist-info/top_level.txt
nhm_pyportal-0.1.dist-info/RECORD
