Metadata-Version: 2.1
Name: nhm-pyportal
Version: 0.1
Summary: UNKNOWN
Home-page: https://github.com/NaturalHistoryMuseum/nhm-pyportal
Author: Natural History Museum
Author-email: data@nhm.ac.uk
License: MIT
Platform: UNKNOWN
Classifier: Development Status :: 3 - Alpha
Classifier: Programming Language :: Python
Classifier: Programming Language :: Python :: 3
Classifier: Topic :: Utilities
Requires-Dist: requests
